MANIFEST.in
README.rst
setup.cfg
setup.py
scrapyrefs/__init__.py
scrapyrefs/scrapyrefs.py
scrapyrefs.egg-info/PKG-INFO
scrapyrefs.egg-info/SOURCES.txt
scrapyrefs.egg-info/dependency_links.txt
scrapyrefs.egg-info/entry_points.txt
scrapyrefs.egg-info/requires.txt
scrapyrefs.egg-info/top_level.txt
scrapyrefs/deps/cermine-impl-1.13-jar-with-dependencies.jar
scrapyrefs/xsl/refs_to_txt.xsl
tests/__init__.py
tests/test_scrapyrefs.py
tests/fixtures/1043637ar.cermxml
tests/fixtures/1043637ar.pdf
tests/fixtures/1043637ar.txt