Metadata-Version: 1.2
Name: scrapyrefs
Version: 0.6.0
Summary: Library that implements the endpoints of the Crossref API
Home-page: http://github.com/erudit/scrapyrefs
Author: Erudit
Author-email: fabio.batalha@erudit.org
Maintainer: Fabio Batalha
Maintainer-email: fabio.batalha@erudit.org
License: UNKNOWN
Platform: UNKNOWN
Classifier: Development Status :: 4 - Beta
Classifier: Intended Audience :: Developers
Classifier: Programming Language :: Python :: 3
